luamb/__init__.py
luamb/__main__.py
luamb/_datadirs.py
luamb/_entrypoint.py
luamb/_exceptions.py
luamb/_hererocks.py
luamb/_luamb.py
luamb/_shell.py
luamb-0.5.0.dist-info/LICENSE
luamb-0.5.0.dist-info/METADATA
luamb-0.5.0.dist-info/WHEEL
luamb-0.5.0.dist-info/entry_points.txt
luamb-0.5.0.dist-info/top_level.txt
luamb-0.5.0.dist-info/zip-safe
luamb-0.5.0.dist-info/RECORD
