Metadata-Version: 2.1
Name: luamb
Version: 0.5.0
Summary: Lua environment manager
Author-email: Dmitry Meyer <me@undef.im>
License: MIT
Project-URL: Homepage, https://github.com/un-def/luamb
Project-URL: Repository, https://github.com/un-def/luamb.git
Project-URL: Changelog, https://github.com/un-def/luamb/blob/master/CHANGELOG.md
Project-URL: Issues, https://github.com/un-def/luamb/issues
Classifier: Intended Audience :: Developers
Classifier: License :: OSI Approved :: MIT License
Classifier: Operating System :: POSIX :: Linux
Classifier: Operating System :: MacOS
Classifier: Programming Language :: Python
Classifier: Programming Language :: Python :: 3
Classifier: Programming Language :: Python :: 3 :: Only
Classifier: Programming Language :: Python :: 3.8
Classifier: Programming Language :: Python :: 3.9
Classifier: Programming Language :: Python :: 3.10
Classifier: Programming Language :: Python :: 3.11
Classifier: Programming Language :: Python :: 3.12
Requires-Python: >=3.8
License-File: LICENSE
